COPYING
README
pyproject.toml
setup.cfg
setup.py
vmodes/__init__.py
vmodes/const.py
vmodes/crc.py
vmodes/ctor.py
vmodes/py.typed
vmodes/types.py
vmodes/util.py
vmodes.egg-info/PKG-INFO
vmodes.egg-info/SOURCES.txt
vmodes.egg-info/dependency_links.txt
vmodes.egg-info/requires.txt
vmodes.egg-info/top_level.txt
vmodes/decoder/__init__.py
vmodes/decoder/_data.c
vmodes/decoder/_data.pxd
vmodes/decoder/_data.pyi
vmodes/decoder/_data.pyx
vmodes/decoder/_position.c
vmodes/decoder/_position.pyi
vmodes/decoder/_position.pyx
vmodes/decoder/aircraft.py
vmodes/decoder/altitude.py
vmodes/decoder/msg_info.py
vmodes/decoder/position.py
vmodes/tests/__init__.py
vmodes/tests/conftest.py
vmodes/tests/data.py
vmodes/tests/test_crc.py
vmodes/tests/test_decoder_aircraft.py
vmodes/tests/test_decoder_altitude.py
vmodes/tests/test_decoder_position.py
vmodes/tests/test_msg_info.py
vmodes/tests/test_util.py