Metadata-Version: 2.4
Name: vmodes
Version: 0.10.0
Summary: VModeS - vectorized decoding of Mode S and ADS-B data
Home-page: https://gitlab.com/sq1090/vmodes
Author: Artur Wroblewski
Author-email: wrobell@riseup.net
License: AGPL-3.0-or-later
Project-URL: Source Code, https://gitlab.com/sq1090/vmodes
Project-URL: Bug tracker, https://gitlab.com/sq1090/vmodes/issues
Classifier: Topic :: Software Development :: Libraries
Classifier: Programming Language :: Python
Classifier: Programming Language :: Python :: 3
Classifier: Development Status :: 3 - Alpha
Requires-Python: >=3.13
License-File: COPYING
Requires-Dist: numpy>=2.4.0
Provides-Extra: tests
Requires-Dist: mypy==1.19.1; extra == "tests"
Requires-Dist: ruff; extra == "tests"
Requires-Dist: pytest-cov; extra == "tests"
Requires-Dist: pytest-timeout; extra == "tests"
Requires-Dist: pytest-asyncio; extra == "tests"
Requires-Dist: types-setuptools; extra == "tests"
Dynamic: license-file
